hashsum.py
hashsum-1.4.1.dist-info/LICENSE.txt
hashsum-1.4.1.dist-info/METADATA
hashsum-1.4.1.dist-info/WHEEL
hashsum-1.4.1.dist-info/entry_points.txt
hashsum-1.4.1.dist-info/top_level.txt
hashsum-1.4.1.dist-info/zip-safe
hashsum-1.4.1.dist-info/RECORD
