Metadata-Version: 2.1
Name: hashsum
Version: 1.4.1
Summary: Python drop-in replacement for md5sum and co.
Home-page: https://github.com/avalentino/hashsum
Author: Antonio Valentino
Author-email: antonio.valentino@tiscli.it
License: BSD 3-Clause License
Download-URL: https://pypi.python.org/pypi/hashsum
Keywords: checksum,hash
Platform: any
Classifier: Development Status :: 5 - Production/Stable
Classifier: Intended Audience :: End Users/Desktop
Classifier: Topic :: Utilities
Classifier: License :: OSI Approved :: BSD License
Classifier: Programming Language :: Python :: 3
Classifier: Programming Language :: Python :: 3.6
Classifier: Programming Language :: Python :: 3.7
Classifier: Programming Language :: Python :: 3.8
Classifier: Programming Language :: Python :: 3.9
Classifier: Programming Language :: Python :: Implementation :: PyPy
Classifier: Operating System :: OS Independent
Requires-Python: >=3.6
License-File: LICENSE.txt
Provides-Extra: cli
Requires-Dist: aurgcomplete ; extra == 'cli'
